Workbook

Sheet Cover
B12: Financial Analysis Model
B14: Table of Contents:
C16: Financial Statements
C18: Ratios
C20: 3-Step DuPont
C22: 5-Step DuPont
C25: Disclaimer:
C26: The following workbook and each cell in it has been protected using a password. It has been done so to preserve the formatting, formulas
C27: and ultimately the dynamicity of the model.
C28: If need be, suggestions and reviews can be made via E-Mail and Linkedin.
C29: Thank You, Have a Nice Day

Sheet Financial Statements
B8: Income Statement
B10: All figures in INR Crores unless stated | J10: 2019 | K10: 2020 | L10: 2021 | M10: 2022 | N10: 2023 | O10: 2024
B12: Revenue | J12: =DATA!C6 -> 146463 | K12: =DATA!D6 -> 156949 | L12: =DATA!E6 -> 164177 | M12: =DATA!F6 -> 191754 | N12: =DATA!G6 -> 225458 | O12: =DATA!H6 -> 240893
B13: COGS | J13: =-SUM(DATA!C10:C12, DATA!C14:C17) -> -83509 | K13: =-SUM(DATA!D10:D12, DATA!D14:D17) -> -89635 | L13: =-SUM(DATA!E10:E12, DATA!E14:E17) -> -94053 | M13: =-SUM(DATA!F10:F12, DATA!F14:F17) -> -111053 | N13: =-SUM(DATA!G10:G12, DATA!G14:G17) -> -132448 | O13: =-SUM(DATA!H10:H12, DATA!H14:H17) -> -139775
B14: Gross Profit | J14: =SUM(J12:J13) -> 62954 | K14: =SUM(K12:K13) -> 67314 | L14: =SUM(L12:L13) -> 70124 | M14: =SUM(M12:M13) -> 80701 | N14: =SUM(N12:N13) -> 93010 | O14: =SUM(O12:O13) -> 101118
B17: SG&A | J17: =-SUM(DATA!C24:C26, DATA!C28:C31) -> -23449 | K17: =-SUM(DATA!D24:D26, DATA!D28:D31) -> -25204 | L17: =-SUM(DATA!E24:E26, DATA!E28:E31) -> -23578 | M17: =-SUM(DATA!F24:F26, DATA!F28:F31) -> -27644 | N17: =-SUM(DATA!G24:G26, DATA!G28:G31) -> -33750 | O17: =-SUM(DATA!H24:H26, DATA!H28:H31) -> -36823
B18: EBITDA | J18: =SUM(J14,J17) -> 39505 | K18: =SUM(K14,K17) -> 42110 | L18: =SUM(L14,L17) -> 46546 | M18: =SUM(M14,M17) -> 53057 | N18: =SUM(N14,N17) -> 59260 | O18: =SUM(O14,O17) -> 64295
B21: Depreciation and Amortisation | J21: =-SUM(DATA!C13,DATA!C27) -> -2055 | K21: =-SUM(DATA!D13,DATA!D27) -> -3530 | L21: =-SUM(DATA!E13,DATA!E27) -> -4065 | M21: =-SUM(DATA!F13,DATA!F27) -> -4604 | N21: =-SUM(DATA!G13,DATA!G27) -> -5023 | O21: =-SUM(DATA!H13,DATA!H27) -> -4984
B22: Other Income/(Expenses) | J22: =DATA!C36 -> 4113 | K22: =DATA!D36 -> 3668 | L22: =DATA!E36 -> 2497 | M22: =DATA!F36 -> 3234 | N22: =DATA!G36 -> 2670 | O22: =DATA!H36 -> 3727
B23: EBIT | J23: =SUM(J18, J21:J22) -> 41563 | K23: =SUM(K18, K21:K22) -> 42248 | L23: =SUM(L18, L21:L22) -> 44978 | M23: =SUM(M18, M21:M22) -> 51687 | N23: =SUM(N18, N21:N22) -> 56907 | O23: =SUM(O18, O21:O22) -> 63038
B26: Interest Expense | J26: =DATA!C45 -> -90 | K26: =DATA!D45 -> -107 | L26: =DATA!E45 -> -132 | M26: =DATA!F45 -> -122 | N26: =DATA!G45 -> -156 | O26: =DATA!H45 -> -191
B27: Interest Income | J27: 0 | K27: 0 | L27: 0 | M27: 0 | N27: 0 | O27: 0
B28: Exceptional Expense | J28: 0 | K28: 0 | L28: 0 | M28: 0 | N28: 0 | O28: 0
B29: EBT | J29: =SUM(J23, J26:J28) -> 41473 | K29: =SUM(K23, K26:K28) -> 42141 | L29: =SUM(L23, L26:L28) -> 44846 | M29: =SUM(M23, M26:M28) -> 51565 | N29: =SUM(N23, N26:N28) -> 56751 | O29: =SUM(O23, O26:O28) -> 62847
B32: Current Tax | J32: =-DATA!C40 -> -10001 | K32: =-DATA!D40 -> -9801 | L32: =-DATA!E40 -> -11458 | M32: =-DATA!F40 -> -13238 | N32: =-DATA!G40 -> -14604 | O32: =-DATA!H40 -> -16262
B33: Total Tax | J33: =SUM(J32) -> -10001 | K33: =SUM(K32) -> -9801 | L33: =SUM(L32) -> -11458 | M33: =SUM(M32) -> -13238 | N33: =SUM(N32) -> -14604 | O33: =SUM(O32) -> -16262
B36: Net Income | J36: =SUM(J29, J33) -> 31472 | K36: =SUM(K29, K33) -> 32340 | L36: =SUM(L29, L33) -> 33388 | M36: =SUM(M29, M33) -> 38327 | N36: =SUM(N29, N33) -> 42147 | O36: =SUM(O29, O33) -> 46585
B38: No of Equity Shares | J38: 375.24 | K38: 375.24 | L38: 369.91 | M38: 365.91 | N38: 365.91 | O38: 361.81
B39: Earning per Share | J39: =J36 / J38 -> 83.871655 | K39: =K36 / K38 -> 86.184842 | L39: =L36 / L38 -> 90.259793 | M39: =M36 / M38 -> 104.74434 | N39: =N36 / N38 -> 115.18406 | O39: =O36 / O38 -> 128.75542
B41: Dividends | J41: =I115 + J36 - J115 -> 27111 | K41: =J115 + K36 - K115 -> 39023 | L41: =K115 + L36 - L115 -> 32575 | M41: =L115 + M36 - M115 -> 40023 | N41: =M115 + N36 - N115 -> 45602 | O41: =N115 + O36 - O115 -> 51253
B44: Cash Flow Statement
B46: All figures in INR Crores unless stated | J46: 2019 | K46: 2020 | L46: 2021 | M46: 2022 | N46: 2023 | O46: 2024
B48: CASH FROM OPERATING
B49: Net Income | J49: =J36 -> 31472 | K49: =K36 -> 32340 | L49: =L36 -> 33388 | M49: =M36 -> 38327 | N49: =N36 -> 42147 | O49: =O36 -> 46585
B50: Depreciation | J50: =-J21 -> 2055 | K50: =-K21 -> 3530 | L50: =-L21 -> 4065 | M50: =-M21 -> 4604 | N50: =-N21 -> 5023 | O50: =-O21 -> 4984
B51: Cash From Accounts Receivable | J51: =I89 - J89 -> -874 | K51: =J89 - K89 -> -3761 | L51: =K89 - L89 -> -398 | M51: =L89 - M89 -> -5148 | N51: =M89 - N89 -> -8144 | O51: =N89 - O89 -> -3623
B52: Change in Other Current Assets | J52: =I90 - J90 -> -7692 | K52: =J90 - K90 -> 7077 | L52: =K90 - L90 -> -10433 | M52: =L90 - M90 -> 1748 | N52: =M90 - N90 -> 819 | O52: =N90 - O90 -> 2802
B53: Cash From Accounts Payable | J53: =J102 - I102 -> 1198 | K53: =K102 - J102 -> 448 | L53: =L102 - K102 -> 1120 | M53: =M102 - L102 -> 185 | N53: =N102 - M102 -> 2470 | O53: =O102 - N102 -> -534
B54: Cash From Other Current Liabilities | J54: =J103 - I103 -> 3058 | K54: =K103 - J103 -> 4528 | L54: =L103 - K103 -> 5975 | M54: =M103 - L103 -> 8011 | N54: =N103 - M103 -> -1263 | O54: =O103 - N103 -> 3080
B55: Other Adjustments | J55: -2212 | K55: 4137 | L55: -2100 | M55: -347 | N55: -640 | O55: -55
B56: Subtotal | J56: =SUM(J49:J55) -> 27005 | K56: =SUM(K49:K55) -> 48299 | L56: =SUM(L49:L55) -> 31617 | M56: =SUM(M49:M55) -> 47380 | N56: =SUM(N49:N55) -> 40412 | O56: =SUM(O49:O55) -> 53239
B59: CASH FROM INVESTING
B60: Capital Expenditure | J60: =I93 - J93 -> -50 | K60: =J93 - K93 -> -288 | L60: =K93 - L93 -> -197 | M60: =L93 - M93 -> 55 | N60: =M93 - N93 -> 485 | O60: =N93 - O93 -> 371
B61: Cash from Other Non-Current Assets | J61: =I94-J94 -> 2313 | K61: =J94-K94 -> -7566 | L61: =K94-L94 -> -628 | M61: =L94-M94 -> -1778 | N61: =M94-N94 -> -660 | O61: =N94-O94 -> -460
B62: Subtotal | J62: =SUM(J60:J61) -> 2263 | K62: =SUM(K60:K61) -> -7854 | L62: =SUM(L60:L61) -> -825 | M62: =SUM(M60:M61) -> -1723 | N62: =SUM(N60:N61) -> -175 | O62: =SUM(O60:O61) -> -89
B65: CASH FROM FINANCING
B66: Dividends | J66: =-J41 -> -27111 | K66: =-K41 -> -39023 | L66: =-L41 -> -32575 | M66: =-M41 -> -40023 | N66: =-N41 -> -45602 | O66: =-O41 -> -51253
B67: Change in Share Capital | J67: =J112 - I112 -> 184 | K67: =K112 - J112 -> 0 | L67: =L112 - K112 -> -5 | M67: =M112 - L112 -> -4 | N67: =N112 - M112 -> 0 | O67: =O112 - N112 -> -4
B68: Change in Share Premium | J68: =J113 - I113 -> 0 | K68: =K113 - J113 -> 0 | L68: =L113 - K113 -> 0 | M68: =M113 - L113 -> 0 | N68: =N113 - M113 -> 0 | O68: =O113 - N113 -> 0
B69: Subtotal | J69: =SUM(J66:J68) -> -26927 | K69: =SUM(K66:K68) -> -39023 | L69: =SUM(L66:L68) -> -32580 | M69: =SUM(M66:M68) -> -40027 | N69: =SUM(N66:N68) -> -45602 | O69: =SUM(O66:O68) -> -51257
B72: CASH BALANCE
B73: Beginning of the Year | J73: =DATA!B73 -> 4883 | K73: =J75 -> 7224 | L73: =K75 -> 8646 | M73: =L75 -> 6858 | N73: =M75 -> 12488 | O73: =N75 -> 7123
B74: Increase / (Decrease) | J74: =SUM(J56,J62,J69) -> 2341 | K74: =SUM(K56,K62,K69) -> 1422 | L74: =SUM(L56,L62,L69) -> -1788 | M74: =SUM(M56,M62,M69) -> 5630 | N74: =SUM(N56,N62,N69) -> -5365 | O74: =SUM(O56,O62,O69) -> 1893
B75: End of the Year | J75: =SUM(J73:J74) -> 7224 | K75: =SUM(K73:K74) -> 8646 | L75: =SUM(L73:L74) -> 6858 | M75: =SUM(M73:M74) -> 12488 | N75: =SUM(N73:N74) -> 7123 | O75: =SUM(O73:O74) -> 9016
O77: “Other Adjustments” captures cash movements within aggregated balance-sheet categories that are not disclosed in detail.
O78: Since these sub-items cannot be separately identified, their combined impact is recorded here as a reconciling entry. (1)
B81: Balance Sheet
B83: All figures in INR Crores unless stated | I83: 2018 | J83: 2019 | K83: 2020 | L83: 2021 | M83: 2022 | N83: 2023 | O83: 2024
B85: ASSETS
B88: Cash | I88: 4883 | J88: =J75 -> 7224 | K88: =K75 -> 8646 | L88: =L75 -> 6858 | M88: =M75 -> 12488 | N88: =N75 -> 7123 | O88: =O75 -> 9016
B89: Accounts Receivable | I89: 31629 | J89: =DATA!C75 + DATA!C78 -> 32503 | K89: =DATA!D75 + DATA!D78 -> 36264 | L89: =DATA!E75 + DATA!E78 -> 36662 | M89: =DATA!F75 + DATA!F78 -> 41810 | N89: =DATA!G75 + DATA!G78 -> 49954 | O89: =DATA!H75 + DATA!H78 -> 53577
B90: Other Current Assets | I90: 44712 | J90: =DATA!C81 - SUM(DATA!C73,DATA!C75,DATA!C78) -> 52404 | K90: =DATA!D81 - SUM(DATA!D73,DATA!D75,DATA!D78) -> 45327 | L90: =DATA!E81 - SUM(DATA!E73,DATA!E75,DATA!E78) -> 55760 | M90: =DATA!F81 - SUM(DATA!F73,DATA!F75,DATA!F78) -> 54012 | N90: =DATA!G81 - SUM(DATA!G73,DATA!G75,DATA!G78) -> 53193 | O90: =DATA!H81 - SUM(DATA!H73,DATA!H75,DATA!H78) -> 50391
B91: Total Current Assets | I91: 81224 | J91: =SUM(J88:J90) -> 92131 | K91: =SUM(K88:K90) -> 90237 | L91: =SUM(L88:L90) -> 99280 | M91: =SUM(M88:M90) -> 108310 | N91: =SUM(N88:N90) -> 110270 | O91: =SUM(O88:O90) -> 112984
B93: Property Plant & Equipment | I93: 11600 | J93: =DATA!C88 -> 11650 | K93: =DATA!D88 -> 11938 | L93: =DATA!E88 -> 12135 | M93: =DATA!F88 -> 12080 | N93: =DATA!G88 -> 11595 | O93: =DATA!H88 -> 11224
B94: Other Non Current Assets | I94: 15585 | J94: =DATA!C96 - DATA!C88 -> 13272 | K94: =DATA!D96 - DATA!D88 -> 20838 | L94: =DATA!E96 - DATA!E88 -> 21466 | M94: =DATA!F96 - DATA!F88 -> 23244 | N94: =DATA!G96 - DATA!G88 -> 23904 | O94: =DATA!H96 - DATA!H88 -> 24364
B95: Total Non Current Assets | I95: 27185 | J95: =SUM(J93:J94) -> 24922 | K95: =SUM(K93:K94) -> 32776 | L95: =SUM(L93:L94) -> 33601 | M95: =SUM(M93:M94) -> 35324 | N95: =SUM(N93:N94) -> 35499 | O95: =SUM(O93:O94) -> 35588
B97: Total Assets | I97: 108409 | J97: =SUM(J91,J95) -> 117053 | K97: =SUM(K91,K95) -> 123013 | L97: =SUM(L91,L95) -> 132881 | M97: =SUM(M91,M95) -> 143634 | N97: =SUM(N91,N95) -> 145769 | O97: =SUM(O91,O95) -> 148572
B100: LIABILITIES
B102: Accounts Payable | I102: 5094 | J102: =DATA!C104 -> 6292 | K102: =DATA!D104 -> 6740 | L102: =DATA!E104 -> 7860 | M102: =DATA!F104 -> 8045 | N102: =DATA!G104 -> 10515 | O102: =DATA!H104 -> 9981
B103: Other Current Liabilities | I103: 12734 | J103: =DATA!C114 - DATA!C104 -> 15792 | K103: =DATA!D114 - DATA!D104 -> 20320 | L103: =DATA!E114 - DATA!E104 -> 26295 | M103: =DATA!F114 - DATA!F104 -> 34306 | N103: =DATA!G114 - DATA!G104 -> 33043 | O103: =DATA!H114 - DATA!H104 -> 36123
B104: Total Current Liabilities | I104: 17828 | J104: =SUM(J102:J103) -> 22084 | K104: =SUM(K102:K103) -> 27060 | L104: =SUM(L102:L103) -> 34155 | M104: =SUM(M102:M103) -> 42351 | N104: =SUM(N102:N103) -> 43558 | O104: =SUM(O102:O103) -> 46104
B106: Total Non Current Liabilities | I106: 2938 | J106: =DATA!C125 -> 2960 | K106: =DATA!D125 -> 9090 | L106: =DATA!E125 -> 9496 | M106: =DATA!F125 -> 9317 | N106: =DATA!G125 -> 8887 | O106: =DATA!H125 -> 9026
B108: Total Liabilties | I108: 20766 | J108: =SUM(J106,J104) -> 25044 | K108: =SUM(K106,K104) -> 36150 | L108: =SUM(L106,L104) -> 43651 | M108: =SUM(M106,M104) -> 51668 | N108: =SUM(N106,N104) -> 52445 | O108: =SUM(O106,O104) -> 55130
B110: EQUITY
B112: Common Equity | I112: 191 | J112: =DATA!C130 -> 375 | K112: =DATA!D130 -> 375 | L112: =DATA!E130 -> 370 | M112: =DATA!F130 -> 366 | N112: =DATA!G130 -> 366 | O112: =DATA!H130 -> 362
B113: Share Premium | I113: 0 | J113: =DATA!C131 -> 0 | K113: =DATA!D131 -> 0 | L113: =DATA!E131 -> 0 | M113: =DATA!F131 -> 0 | N113: =DATA!G131 -> 0 | O113: =DATA!H131 -> 0
B114: Other Reserves | I114: 2796 | J114: =DATA!C132 -> 2566 | K114: =DATA!D132 -> 3933 | L114: =DATA!E132 -> 5440 | M114: =DATA!F132 -> 9844 | N114: =DATA!G132 -> 14582 | O114: =DATA!H132 -> 19324
B115: Retained Earnings | I115: 84254 | J115: =DATA!C133 -> 88615 | K115: =DATA!D133 -> 81932 | L115: =DATA!E133 -> 82745 | M115: =DATA!F133 -> 81049 | N115: =DATA!G133 -> 77594 | O115: =DATA!H133 -> 72926
B116: Non-Controlling Interest | I116: 402 | J116: =DATA!C136 -> 453 | K116: =DATA!D136 -> 623 | L116: =DATA!E136 -> 675 | M116: =DATA!F136 -> 707 | N116: =DATA!G136 -> 782 | O116: =DATA!H136 -> 830
B117: Total Shareholders' Equity | I117: 87643 | J117: =SUM(J112:J116) -> 92009 | K117: =SUM(K112:K116) -> 86863 | L117: =SUM(L112:L116) -> 89230 | M117: =SUM(M112:M116) -> 91966 | N117: =SUM(N112:N116) -> 93324 | O117: =SUM(O112:O116) -> 93442
B120: Total Liabilities & Equity | I120: 108409 | J120: =J117 + J108 -> 117053 | K120: =K117 + K108 -> 123013 | L120: =L117 + L108 -> 132881 | M120: =M117 + M108 -> 143634 | N120: =N117 + N108 -> 145769 | O120: =O117 + O108 -> 148572
B123: Check | J123: =IF(J120 = J97, 1, 0) -> 1 | K123: =IF(K120 = K97, 1, 0) -> 1 | L123: =IF(L120 = L97, 1, 0) -> 1 | M123: =IF(M120 = M97, 1, 0) -> 1 | N123: =IF(N120 = N97, 1, 0) -> 1 | O123: =IF(O120 = O97, 1, 0) -> 1

Sheet DATA
A1: TCS Consolidated Income Statement as per IFRS - INR Mn | B1: FY18 | C1: FY19 | D1: FY20 | E1: FY21 | F1: FY22 | G1: FY23 | H1: FY24
E2: EX-ADJ *** | H2: EX-ADJ ****
A3: Revenue
A4: Information Technology and Consultancy Services | B4: 123104 | C4: 146463 | D4: 156949 | E4: 164177 | F4: 191754 | G4: 225458 | H4: 240893 | J4: 10
A5: Sale of Equipment and Software Licenses | B5: 0 | C5: 0 | D5: 0 | E5: 0 | F5: 0 | G5: 0 | H5: 0
A6: Total Revenue | B6: 123104 | C6: 146463 | D6: 156949 | E6: 164177 | F6: 191754 | G6: 225458 | H6: 240893 | K6: Dividends: | L6: 2018 | M6: 2019 | N6: 2020 | O6: 2021 | P6: 2022 | Q6: 2023 | R6: 2024
B7: 0 | C7: 0 | D7: 0 | E7: 0 | F7: 0 | G7: 0 | H7: 0 | M7: 11424 | N7: 37634 | O7: 10850 | P7: 13317 | Q7: 41347 | R7: 25137
A8: Cost of Revenues | B8: 0 | C8: 0 | D8: 0 | E8: 0 | F8: 0 | G8: 0 | H8: 0
A9: Cost of Services | B9: 0 | C9: 0 | D9: 0 | E9: 0 | F9: 0 | G9: 0 | H9: 0
A10: Employee Cost | B10: 50350 | C10: 60553 | D10: 65652 | E10: 71946 | F10: 84135 | G10: 99147 | H10: 109244
A11: Fees to External Consultants | B11: 8431 | C11: 10686 | D11: 12500 | E11: 12648 | F11: 16795 | G11: 20642 | H11: 14986
A12: Cost of Equipment and Software Licenses | B12: 2700 | C12: 2270 | D12: 1905 | E12: 1462 | F12: 1163 | G12: 1881 | H12: 3702
A13: Depreciation | B13: 1573 | C13: 1649 | D13: 2687 | E13: 3085 | F13: 3568 | G13: 3820 | H13: 3820
A14: Travel | B14: 1876 | C14: 2334 | D14: 2291 | E14: 883 | F14: 1294 | G14: 1815 | H14: 2059
A15: Communication | B15: 791 | C15: 984 | D15: 1232 | E15: 1434 | F15: 1537 | G15: 1500 | H15: 1475
A16: Facility Expenses | B16: 2646 | C16: 2984 | D16: 1798 | E16: 1401 | F16: 1354 | G16: 1651 | H16: 1926
A17: Other Costs | B17: 2921 | C17: 3698 | D17: 4257 | E17: 4279 | F17: 4775 | G17: 5812 | H17: 6383
A18: Total Cost of Revenues | B18: 71288 | C18: 85158 | D18: 92322 | E18: 97138 | F18: 114621 | G18: 136268 | H18: 143595
B19: 0 | C19: 0 | D19: 0 | E19: 0 | F19: 0 | G19: 0 | H19: 0
A20: Gross Profit | B20: 51816 | C20: 61305 | D20: 64627 | E20: 67039 | F20: 77133 | G20: 89190 | H20: 97298
B21: 0 | C21: 0 | D21: 0 | E21: 0 | F21: 0 | G21: 0 | H21: 0
A22: Operating Expenses | B22: 0 | C22: 0 | D22: 0 | E22: 0 | F22: 0 | G22: 0 | H22: 0
A23: Selling, General and Administrative Expenses | B23: 0 | C23: 0 | D23: 0 | E23: 0 | F23: 0 | G23: 0 | H23: 0
A24: Employee Cost | B24: 16046 | C24: 17692 | D24: 20300 | E24: 19868 | F24: 23419 | G24: 28375 | H24: 30888
A25: Fees to External Consultants | B25: 559 | C25: 644 | D25: 437 | E25: 569 | F25: 615 | G25: 693 | H25: 834
A26: Provision for Doubtful Debts | B26: 208 | C26: 187 | D26: 144 | E26: 201 | F26: 135 | G26: 139 | H26: 114
A27: Depreciation | B27: 441 | C27: 406 | D27: 843 | E27: 980 | F27: 1036 | G27: 1203 | H27: 1164
A28: Facility Expenses | B28: 1291 | C28: 1278 | D28: 906 | E28: 729 | F28: 785 | G28: 1003 | H28: 1174
A29: Travel | B29: 941 | C29: 1140 | D29: 1004 | E29: 198 | F29: 294 | G29: 861 | H29: 913
A30: Communication | B30: 269 | C30: 338 | D30: 360 | E30: 462 | F30: 514 | G30: 745 | H30: 788
A31: Other Costs | B31: 1559 | C31: 2170 | D31: 2053 | E31: 1551 | F31: 1882 | G31: 1934 | H31: 2112
A32: Total Operating Expenses | B32: 21314 | C32: 23855 | D32: 26047 | E32: 24558 | F32: 28680 | G32: 34953 | H32: 37987
B33: 0 | C33: 0 | D33: 0 | E33: 0 | F33: 0 | G33: 0 | H33: 0
A34: Operating Income | B34: 30502 | C34: 37450 | D34: 38580 | E34: 42481 | F34: 48453 | G34: 54237 | H34: 59311
B35: 0 | C35: 0 | D35: 0 | E35: 0 | F35: 0 | G35: 0 | H35: 0
A36: Total Other Income/(Expense) | B36: 3590 | C36: 4113 | D36: 3668 | E36: 2497 | F36: 3234 | G36: 2670 | H36: 3727
B37: 0 | C37: 0 | D37: 0 | E37: 0 | F37: 0 | G37: 0 | H37: 0
A38: Income Before Income Taxes | B38: 34092 | C38: 41563 | D38: 42248 | E38: 44978 | F38: 51687 | G38: 56907 | H38: 63038
B39: 0 | C39: 0 | D39: 0 | E39: 0 | F39: 0 | G39: 0 | H39: 0
A40: Total Taxes | B40: 8212 | C40: 10001 | D40: 9801 | E40: 11458 | F40: 13238 | G40: 14604 | H40: 16262
B41: 0 | C41: 0 | D41: 0 | E41: 0 | F41: 0 | G41: 0 | H41: 0
A42: Net Profit After Taxes | B42: 25880 | C42: 31562 | D42: 32447 | E42: 33520 | F42: 38449 | G42: 42303 | H42: 46776
B43: 0 | C43: 0 | D43: 0 | E43: 0 | F43: 0 | G43: 0 | H43: 0
A44: Adjustments for Minority Interests | B44: 0 | C44: 0 | D44: 0 | E44: 0 | F44: 0 | G44: 0 | H44: 0
A45: Non-controlling interests | B45: -54 | C45: -90 | D45: -107 | E45: -132 | F45: -122 | G45: -156 | H45: -191
B46: 0 | C46: 0 | D46: 0 | E46: 0 | F46: 0 | G46: 0 | H46: 0
A47: Net Income Before Extraordinary Items | B47: 25826 | C47: 31472 | D47: 32340 | E47: 33388 | F47: 38327 | G47: 42147 | H47: 46585
B48: 0 | C48: 0 | D48: 0 | E48: 0 | F48: 0 | G48: 0 | H48: 0
A49: Net Income After Extraordinary Items | B49: 25826 | C49: 31472 | D49: 32340 | E49: 33388 | F49: 38327 | G49: 42147 | H49: 46585
B50: 0 | C50: 0 | D50: 0 | E50: 0 | F50: 0 | G50: 0 | H50: 0
B51: 0 | C51: 0 | D51: 0 | E51: 0 | F51: 0 | G51: 0 | H51: 0
A52: Basic and Diluted EPS (after adjusting for bonus shares) | B52: 13.419 | C52: 8.305 | D52: 8.619 | E52: 8.927 | F52: 10.362 | G52: 11.519 | H52: 12.774
B53: 0 | C53: 0 | D53: 0 | E53: 0 | F53: 0 | G53: 0 | H53: 0
A54: Dividend Per share (INR) | B54: 5 | C54: 3 | D54: 7.3 | E54: 3.8 | F54: 4.3 | G54: 11.5 | H54: 7.3
B55: 0 | C55: 0 | D55: 0 | E55: 0 | F55: 0 | G55: 0 | H55: 0
B56: 0 | C56: 0 | D56: 0 | E56: 0 | F56: 0 | G56: 0 | H56: 0
B57: 0 | C57: 0 | D57: 0 | E57: 0 | F57: 0 | G57: 0 | H57: 0
A58: Weighted average no of shares used in computing Basic and Diluted EPS | B58: 1.9245928e+08 | C58: 378974935 | D58: 3.7523847e+08 | E58: 3.7401107e+08 | F58: 3.6988322e+08 | G58: 3.6590514e+08 | H58: 3.6468518e+08
B59: 0 | C59: 0 | D59: 0 | E59: 0 | F59: 0 | G59: 0 | H59: 0
B60: 0 | C60: 0 | D60: 0 | E60: 0 | F60: 0 | G60: 0 | H60: 0
B61: 0 | C61: 0 | D61: 0 | E61: 0 | F61: 0 | G61: 0 | H61: 0
A62: Back | B62: 0 | C62: 0 | D62: 0 | E62: 0 | F62: 0 | G62: 0 | H62: 0
B63: 0 | C63: 0 | D63: 0 | E63: 0 | F63: 0 | G63: 0 | H63: 0
B64: 0 | C64: 0 | D64: 0 | E64: 0 | F64: 0 | G64: 0 | H64: 0
B65: 0 | C65: 0 | D65: 0 | E65: 0 | F65: 0 | G65: 0 | H65: 0
B66: 0 | C66: 0 | D66: 0 | E66: 0 | F66: 0 | G66: 0 | H66: 0
A67: TCS Consolidated Balance Sheet as per IFRS - INR Mn | B67: FY18 | C67: FY19 | D67: FY20 | E67: FY21 | F67: FY22 | G67: FY23 | H67: FY24
A68: Period Ending | B68: 4319 | C68: 4355.5 | D68: 4392.1 | E68: 4428.6 | F68: 4465.1 | G68: 4501.6 | H68: 4538.2
B69: 0 | C69: 0 | D69: 0 | E69: 0 | F69: 0 | G69: 0 | H69: 0
A70: ASSETS | B70: 0 | C70: 0 | D70: 0 | E70: 0 | F70: 0 | G70: 0 | H70: 0
B71: 0 | C71: 0 | D71: 0 | E71: 0 | F71: 0 | G71: 0 | H71: 0
A72: Current Assets | B72: 0 | C72: 0 | D72: 0 | E72: 0 | F72: 0 | G72: 0 | H72: 0
A73: Cash and Cash Equivalents | B73: 4883 | C73: 7224 | D73: 8646 | E73: 6858 | F73: 12488 | G73: 7123 | H73: 9016
A74: Bank Deposits | B74: 2056 | C74: 5428 | D74: 805 | E74: 2262 | F74: 5507 | G74: 3224 | H74: 3799
A75: Trade Receivables | B75: 24943 | C75: 27346 | D75: 30532 | E75: 30079 | F75: 34074 | G75: 41049 | H75: 44434
A76: Investments | B76: 35707 | C76: 29091 | D76: 26140 | E76: 29160 | F76: 30262 | G76: 36897 | H76: 31481
A77: Other Current Financial Assets | B77: 4302 | C77: 9994 | D77: 10163 | E77: 13075 | F77: 8061 | G77: 3329 | H77: 2665
A78: Unbilled Receivables (PY: Unbilled Revenue) | B78: 6686 | C78: 5157 | D78: 5732 | E78: 6583 | F78: 7736 | G78: 8905 | H78: 9143
A79: Current Income Tax assets | B79: 37 | C79: 1853 | D79: 8 | E79: 19 | F79: 11 | G79: 8 | H79: 151
A80: Other Current Assets | B80: 2610 | C80: 6038 | D80: 8211 | E80: 11244 | F80: 10171 | G80: 9735 | H80: 12295
A81: Total Current Assets | B81: 81224 | C81: 92131 | D81: 90237 | E81: 99280 | F81: 108310 | G81: 110270 | H81: 112984
B82: 0 | C82: 0 | D82: 0 | E82: 0 | F82: 0 | G82: 0 | H82: 0
A83: Non Current assets | B83: 0 | C83: 0 | D83: 0 | E83: 0 | F83: 0 | G83: 0 | H83: 0
A84: Bank Deposits | B84: 0 | C84: 0 | D84: 348 | E84: 719 | F84: 1232 | G84: 1334 | H84: 2248
A85: Other Non Current Financial Assets | B85: 2667 | C85: 798 | D85: 865 | E85: 883 | F85: 1332 | G85: 988 | H85: 1026
A86: Non Current Income Tax Assets | B86: 4131 | C86: 4017 | D86: 2462 | E86: 1845 | F86: 1983 | G86: 2583 | H86: 1600
A87: Deferred Income Tax Assets | B87: 3423 | C87: 2632 | D87: 2802 | E87: 3903 | F87: 3680 | G87: 3277 | H87: 3369
A88: Property, Plant and Equipment, net | B88: 11600 | C88: 11650 | D88: 11938 | E88: 12135 | F88: 12080 | G88: 11595 | H88: 11224
A89: Right-of-use assets | B89: 0 | C89: 0 | D89: 7994 | E89: 7633 | F89: 7636 | G89: 7560 | H89: 7886
A90: Goodwill, net | B90: 3884 | C90: 3834 | D90: 3850 | E90: 3948 | F90: 3935 | G90: 4006 | H90: 3989
A91: Other Intangible Assets, net | B91: 12 | C91: 179 | D91: 283 | E91: 480 | F91: 1101 | G91: 867 | H91: 510
A92: Investments | B92: 301 | C92: 239 | D92: 216 | E92: 213 | F92: 223 | G92: 266 | H92: 281
A93: Trade Receivables | B93: 94 | C93: 95 | D93: 74 | E93: 55 | F93: 145 | G93: 149 | H93: 127
A94: Unbilled Receivables (PY: Unbilled Revenue) | B94: 227 | C94: 391 | D94: 324 | E94: 273 | F94: 55 | G94: 199 | H94: 16
... A96: Total Non-Current Assets | B96: 27185 | C96: 24922 | D96: 32776 | E96: 33601 | F96: 35324 | G96: 35499 | H96: 35588
B97: 0 | C97: 0 | D97: 0 | E97: 0 | F97: 0 | G97: 0 | H97: 0
A98: Total Assets | B98: 108409 | C98: 117053 | D98: 123013 | E98: 132881 | F98: 143634 | G98: 145769 | H98: 148572
B99: 0 | C99: 0 | D99: 0 | E99: 0 | F99: 0 | G99: 0 | H99: 0
A100: LIABILITIES AND SHAREHOLDER'S EQUITY | B100: 0 | C100: 0 | D100: 0 | E100: 0 | F100: 0 | G100: 0 | H100: 0
B101: 0 | C101: 0 | D101: 0 | E101: 0 | F101: 0 | G101: 0 | H101: 0
...

Sheet Ratios
B8: 3-Step DuPont Analysis
B10: All figures in INR Crores unless stated | J10: 2019 | K10: 2020 | L10: 2021 | M10: 2022 | N10: 2023 | O10: 2024 | Q10: Trend
B12: Net Profit Margin | D12: = | E12: Net Income | H12: = | J12: ='Financial Statements'!J36/'Financial Statements'!J12 -> 0.21488021 | K12: ='Financial Statements'!K36/'Financial Statements'!K12 -> 0.2060542 | L12: ='Financial Statements'!L36/'Financial Statements'!L12 -> 0.20336588 | M12: ='Financial Statements'!M36/'Financial Statements'!M12 -> 0.19987588 | N12: ='Financial Statements'!N36/'Financial Statements'!N12 -> 0.18693947 | O12: ='Financial Statements'!O36/'Financial Statements'!O12 -> 0.19338461
E13: Revenue
B15: Asset Turnover | D15: = | E15: Revenue | H15: = | J15: ='Financial Statements'!J12 / 'Financial Statements'!J97 -> 1.2512537 | K15: ='Financial Statements'!K12 / 'Financial Statements'!K97 -> 1.2758733 | L15: ='Financial Statements'!L12 / 'Financial Statements'!L97 -> 1.235519 | M15: ='Financial Statements'!M12 / 'Financial Statements'!M97 -> 1.3350182 | N15: ='Financial Statements'!N12 / 'Financial Statements'!N97 -> 1.54668 | O15: ='Financial Statements'!O12 / 'Financial Statements'!O97 -> 1.621389
E16: Total Assets
B18: Equity Multiplier | D18: = | E18: Total Assets | H18: = | J18: ='Financial Statements'!J97 / 'Financial Statements'!J117 -> 1.2721908 | K18: ='Financial Statements'!K97 / 'Financial Statements'!K117 -> 1.4161726 | L18: ='Financial Statements'!L97 / 'Financial Statements'!L117 -> 1.4891965 | M18: ='Financial Statements'!M97 / 'Financial Statements'!M117 -> 1.5618163 | N18: ='Financial Statements'!N97 / 'Financial Statements'!N117 -> 1.5619669 | O18: ='Financial Statements'!O97 / 'Financial Statements'!O117 -> 1.5899917
E19: Total Shareholders' Equity
B23: 5-Step DuPont Analysis
B25: All figures in INR Crores unless stated | J25: 2019 | K25: 2020 | L25: 2021 | M25: 2022 | N25: 2023 | O25: 2024 | Q25: Trend
B27: Tax Burden | D27: = | E27: Net Income | H27: = | J27: ='Financial Statements'!J36/'Financial Statements'!J29 -> 0.75885516 | K27: ='Financial Statements'!K36/'Financial Statements'!K29 -> 0.76742365 | L27: ='Financial Statements'!L36/'Financial Statements'!L29 -> 0.74450341 | M27: ='Financial Statements'!M36/'Financial Statements'!M29 -> 0.74327548 | N27: ='Financial Statements'!N36/'Financial Statements'!N29 -> 0.74266533 | O27: ='Financial Statements'!O36/'Financial Statements'!O29 -> 0.74124461
E28: Earnings Before Tax
B30: Interest Burden | D30: = | E30: Earnings Before Tax | H30: = | J30: ='Financial Statements'!J29 / 'Financial Statements'!J23 -> 0.99783461 | K30: ='Financial Statements'!K29 / 'Financial Statements'!K23 -> 0.99746734 | L30: ='Financial Statements'!L29 / 'Financial Statements'!L23 -> 0.99706523 | M30: ='Financial Statements'!M29 / 'Financial Statements'!M23 -> 0.99763964 | N30: ='Financial Statements'!N29 / 'Financial Statements'!N23 -> 0.99725869 | O30: ='Financial Statements'!O29 / 'Financial Statements'!O23 -> 0.99697008
E31: EBIT
B33: EBIT Margin | D33: = | E33: EBIT | H33: = | J33: ='Financial Statements'!J23 / 'Financial Statements'!J12 -> 0.28377816 | K33: ='Financial Statements'!K23 / 'Financial Statements'!K12 -> 0.26918298 | L33: ='Financial Statements'!L23 / 'Financial Statements'!L12 -> 0.27396042 | M33: ='Financial Statements'!M23 / 'Financial Statements'!M12 -> 0.26954848 | N33: ='Financial Statements'!N23 / 'Financial Statements'!N12 -> 0.25240621 | O33: ='Financial Statements'!O23 / 'Financial Statements'!O12 -> 0.26168465
E34: Revenue
B36: Asset Turnover | D36: = | E36: Revenue | H36: = | J36: ='Financial Statements'!J12 / 'Financial Statements'!J97 -> 1.2512537 | K36: ='Financial Statements'!K12 / 'Financial Statements'!K97 -> 1.2758733 | L36: ='Financial Statements'!L12 / 'Financial Statements'!L97 -> 1.235519 | M36: ='Financial Statements'!M12 / 'Financial Statements'!M97 -> 1.3350182 | N36: ='Financial Statements'!N12 / 'Financial Statements'!N97 -> 1.54668 | O36: ='Financial Statements'!O12 / 'Financial Statements'!O97 -> 1.621389
E37: Total Assets
B39: Equity Multiplier | D39: = | E39: Total Assets | H39: = | J39: ='Financial Statements'!J97 / 'Financial Statements'!J117 -> 1.2721908 | K39: ='Financial Statements'!K97 / 'Financial Statements'!K117 -> 1.4161726 | L39: ='Financial Statements'!L97 / 'Financial Statements'!L117 -> 1.4891965 | M39: ='Financial Statements'!M97 / 'Financial Statements'!M117 -> 1.5618163 | N39: ='Financial Statements'!N97 / 'Financial Statements'!N117 -> 1.5619669 | O39: ='Financial Statements'!O97 / 'Financial Statements'!O117 -> 1.5899917
E40: Total Shareholders' Equity

Sheet 3-Step DuPont
L8: Return On Equity
J9: 2019 | K9: 2020 | L9: 2021 | M9: 2022 | N9: 2023 | O9: 2024
J10: =B17 * J17 * R17 -> 0.34205349 | K10: =C17 * K17 * S17 -> 0.37231042 | L10: =D17 * L17 * T17 -> 0.37417909 | M10: =E17 * M17 * U17 -> 0.41675184 | N10: =F17 * N17 * V17 -> 0.45162016 | O10: =G17 * O17 * W17 -> 0.49854455
D15: =Ratios!$B$12 -> Net Profit Margin | L15: =Ratios!B15 -> Asset Turnover | T15: =Ratios!B18 -> Equity Multiplier
B16: 2019 | C16: 2020 | D16: 2021 | E16: 2022 | F16: 2023 | G16: 2024 | J16: 2019 | K16: 2020 | L16: 2021 | M16: 2022 | N16: 2023 | O16: 2024 | R16: 2019 | S16: 2020 | T16: 2021 | U16: 2022 | V16: 2023 | W16: 2024
B17: =Ratios!J12 -> 0.21488021 | C17: =Ratios!K12 -> 0.2060542 | D17: =Ratios!L12 -> 0.20336588 | E17: =Ratios!M12 -> 0.19987588 | F17: =Ratios!N12 -> 0.18693947 | G17: =Ratios!O12 -> 0.19338461 | J17: =Ratios!J15 -> 1.2512537 | K17: =Ratios!K15 -> 1.2758733 | L17: =Ratios!L15 -> 1.235519 | M17: =Ratios!M15 -> 1.3350182 | N17: =Ratios!N15 -> 1.54668 | O17: =Ratios!O15 -> 1.621389 | R17: =Ratios!J18 -> 1.2721908 | S17: =Ratios!K18 -> 1.4161726 | T17: =Ratios!L18 -> 1.4891965 | U17: =Ratios!M18 -> 1.5618163 | V17: =Ratios!N18 -> 1.5619669 | W17: =Ratios!O18 -> 1.5899917

Sheet 5-Step DuPont
L7: Return On Equity
J8: 2019 | K8: 2020 | L8: 2021 | M8: 2022 | N8: 2023 | O8: 2024
J9: =B16*F24*J16*N24*R16 -> 0.34205349 | K9: =C16*G24*K16*O24*S16 -> 0.37231042 | L9: =D16*H24*L16*P24*T16 -> 0.37417909 | M9: =E16*I24*M16*Q24*U16 -> 0.41675184 | N9: =F16*J24*N16*R24*V16 -> 0.45162016 | O9: =G16*K24*O16*S24*W16 -> 0.49854455
D14: =Ratios!B27 -> Tax Burden | L14: =Ratios!B33 -> EBIT Margin | T14: =Ratios!B39 -> Equity Multiplier
B15: 2019 | C15: 2020 | D15: 2021 | E15: 2022 | F15: 2023 | G15: 2024 | J15: 2019 | K15: 2020 | L15: 2021 | M15: 2022 | N15: 2023 | O15: 2024 | R15: 2019 | S15: 2020 | T15: 2021 | U15: 2022 | V15: 2023 | W15: 2024
B16: =Ratios!J27 -> 0.75885516 | C16: =Ratios!K27 -> 0.76742365 | D16: =Ratios!L27 -> 0.74450341 | E16: =Ratios!M27 -> 0.74327548 | F16: =Ratios!N27 -> 0.74266533 | G16: =Ratios!O27 -> 0.74124461 | J16: =Ratios!J33 -> 0.28377816 | K16: =Ratios!K33 -> 0.26918298 | L16: =Ratios!L33 -> 0.27396042 | M16: =Ratios!M33 -> 0.26954848 | N16: =Ratios!N33 -> 0.25240621 | O16: =Ratios!O33 -> 0.26168465 | R16: =Ratios!J39 -> 1.2721908 | S16: =Ratios!K39 -> 1.4161726 | T16: =Ratios!L39 -> 1.4891965 | U16: =Ratios!M39 -> 1.5618163 | V16: =Ratios!N39 -> 1.5619669 | W16: =Ratios!O39 -> 1.5899917
H22: =Ratios!B30 -> Interest Burden | P22: =Ratios!B36 -> Asset Turnover
F23: 2019 | G23: 2020 | H23: 2021 | I23: 2022 | J23: 2023 | K23: 2024 | N23: 2019 | O23: 2020 | P23: 2021 | Q23: 2022 | R23: 2023 | S23: 2024
F24: =Ratios!J30 -> 0.99783461 | G24: =Ratios!K30 -> 0.99746734 | H24: =Ratios!L30 -> 0.99706523 | I24: =Ratios!M30 -> 0.99763964 | J24: =Ratios!N30 -> 0.99725869 | K24: =Ratios!O30 -> 0.99697008 | N24: =Ratios!J36 -> 1.2512537 | O24: =Ratios!K36 -> 1.2758733 | P24: =Ratios!L36 -> 1.235519 | Q24: =Ratios!M36 -> 1.3350182 | R24: =Ratios!N36 -> 1.54668 | S24: =Ratios!O36 -> 1.621389
